[
  {
    "id": "af9dc906-4fdf-3e0b-95a1-72eaa9fea6a3",
    "lat": "  -3.272700",
    "lon": " -42.386400",
    "data_hora_gmt": "2025-02-19 00:00:00",
    "satelite": "GOES-16",
    "municipio": "SÃO BERNARDO",
    "estado": "MARANHÃO",
    "pais": "Brasil",
    "municipio_id": "2110609",
    "estado_id": "21",
    "pais_id": "33",
    "numero_dias_sem_chuva": "",
    "precipitacao": "",
    "risco_fogo": "",
    "bioma": "Cerrado",
    "frp": "56.5"
  },
  {
    "id": "2b19ce7d-b88b-3b04-bf59-b81505384a8f",
    "lat": "  -7.094600",
    "lon": " -35.121800",
    "data_hora_gmt": "2025-02-19 00:00:00",
    "satelite": "GOES-16",
    "municipio": "CRUZ DO ESPÍRITO SANTO",
    "estado": "PARAÍBA",
    "pais": "Brasil",
    "municipio_id": "2504900",
    "estado_id": "25",
    "pais_id": "33",
    "numero_dias_sem_chuva": "",
    "precipitacao": "",
    "risco_fogo": "",
    "bioma": "Mata Atlântica",
    "frp": "86.0"
  },
  {
    "id": "6f8b9804-964f-351a-85db-cdc5e71f4a9d",
    "lat": "  -7.094900",
    "lon": " -35.094300",
    "data_hora_gmt": "2025-02-19 00:00:00",
    "satelite": "GOES-16",
    "municipio": "CRUZ DO ESPÍRITO SANTO",
    "estado": "PARAÍBA",
    "pais": "Brasil",
    "municipio_id": "2504900",
    "estado_id": "25",
    "pais_id": "33",
    "numero_dias_sem_chuva": "",
    "precipitacao": "",
    "risco_fogo": "",
    "bioma": "Mata Atlântica",
    "frp": "134.9"
  },
  {
    "id": "d8b6c8b5-c234-3385-89fe-7fe6255585b7",
    "lat": "  -7.399500",
    "lon": " -35.163100",
    "data_hora_gmt": "2025-02-19 00:20:00",
    "satelite": "GOES-16",
    "municipio": "ITAMBÉ",
    "estado": "PERNAMBUCO",
    "pais": "Brasil",
    "municipio_id": "2607653",
    "estado_id": "26",
    "pais_id": "33",
    "numero_dias_sem_chuva": "",
    "precipitacao": "",
    "risco_fogo": "",
    "bioma": "Mata Atlântica",
    "frp": "99.3"
  },
  {
    "id": "5700b829-5c13-3f83-aab9-ab1df7519aa0",
    "lat": " -22.679600",
    "lon": " -42.857300",
    "data_hora_gmt": "2025-02-19 00:28:00",
    "satelite": "METOP-B",
    "municipio": "ITABORAÍ",
    "estado": "RIO DE JANEIRO",
    "pais": "Brasil",
    "municipio_id": "3301900",
    "estado_id": "33",
    "pais_id": "33",
    "numero_dias_sem_chuva": "",
    "precipitacao": "",
    "risco_fogo": "",
    "bioma": "Mata Atlântica",
    "frp": ""
  },
  {
    "id": "f5e27a2d-e875-3552-8259-ca953622fabd",
    "lat": " -13.806300",
    "lon": " -41.709000",
    "data_hora_gmt": "2025-02-19 00:28:00",
    "satelite": "METOP-B",
    "municipio": "DOM BASÍLIO",
    "estado": "BAHIA",
    "pais": "Brasil",
    "municipio_id": "2910107",
    "estado_id": "29",
    "pais_id": "33",
    "numero_dias_sem_chuva": "",
    "precipitacao": "",
    "risco_fogo": "",
    "bioma": "Caatinga",
    "frp": ""
  },
  {
    "id": "2179780e-104e-3087-b11a-4d66f566ccc4",
    "lat": "  -3.275100",
    "lon": " -42.388100",
    "data_hora_gmt": "2025-02-19 00:28:00",
    "satelite": "METOP-B",
    "municipio": "SÃO BERNARDO",
    "estado": "MARANHÃO",
    "pais": "Brasil",
    "municipio_id": "2110609",
    "estado_id": "21",
    "pais_id": "33",
    "numero_dias_sem_chuva": "",
    "precipitacao": "",
    "risco_fogo": "",
    "bioma": "Cerrado",
    "frp": ""
  },
  {
    "id": "9129d347-1661-3dd0-b9a5-cb3e085599b2",
    "lat": " -21.418501",
    "lon": " -48.542000",
    "data_hora_gmt": "2025-02-19 00:28:00",
    "satelite": "METOP-B",
    "municipio": "TAQUARITINGA",
    "estado": "SÃO PAULO",
    "pais": "Brasil",
    "municipio_id": "3553708",
    "estado_id": "35",
    "pais_id": "33",
    "numero_dias_sem_chuva": "",
    "precipitacao": "",
    "risco_fogo": "",
    "bioma": "Mata Atlântica",
    "frp": ""
  },
  {
    "id": "ef28fe64-d7eb-3997-859e-3dd23ae8c514",
    "lat": " -10.546300",
    "lon": " -45.213299",
    "data_hora_gmt": "2025-02-19 00:28:00",
    "satelite": "METOP-B",
    "municipio": "CORRENTE",
    "estado": "PIAUÍ",
    "pais": "Brasil",
    "municipio_id": "2202901",
    "estado_id": "22",
    "pais_id": "33",
    "numero_dias_sem_chuva": "",
    "precipitacao": "",
    "risco_fogo": "",
    "bioma": "Cerrado",
    "frp": ""
  },
  {
    "id": "15a2e013-3304-3e8b-b4cf-3da003975ca2",
    "lat": " -11.582400",
    "lon": " -47.632599",
    "data_hora_gmt": "2025-02-19 00:28:00",
    "satelite": "METOP-B",
    "municipio": "NATIVIDADE",
    "estado": "TOCANTINS",
    "pais": "Brasil",
    "municipio_id": "1714203",
    "estado_id": "17",
    "pais_id": "33",
    "numero_dias_sem_chuva": "",
    "precipitacao": "",
    "risco_fogo": "",
    "bioma": "Cerrado",
    "frp": ""
  },
  {
    "id": "18e61018-8f07-3d58-9ebe-72021d67dbb5",
    "lat": " -13.802900",
    "lon": " -41.695400",
    "data_hora_gmt": "2025-02-19 00:28:00",
    "satelite": "METOP-B",
    "municipio": "DOM BASÍLIO",
    "estado": "BAHIA",
    "pais": "Brasil",
    "municipio_id": "2910107",
    "estado_id": "29",
    "pais_id": "33",
    "numero_dias_sem_chuva": "",
    "precipitacao": "",
    "risco_fogo": "",
    "bioma": "Caatinga",
    "frp": ""
  },
  {
    "id": "64280961-4189-33b2-afa3-e359056247c6",
    "lat": "  -3.284800",
    "lon": " -42.385799",
    "data_hora_gmt": "2025-02-19 00:28:00",
    "satelite": "METOP-B",
    "municipio": "SÃO BERNARDO",
    "estado": "MARANHÃO",
    "pais": "Brasil",
    "municipio_id": "2110609",
    "estado_id": "21",
    "pais_id": "33",
    "numero_dias_sem_chuva": "",
    "precipitacao": "",
    "risco_fogo": "",
    "bioma": "Cerrado",
    "frp": ""
  },
  {
    "id": "2d60b0c0-1baf-3b17-9e64-411e9c09a271",
    "lat": " -10.950000",
    "lon": " -45.173599",
    "data_hora_gmt": "2025-02-19 00:28:00",
    "satelite": "METOP-B",
    "municipio": "FORMOSA DO RIO PRETO",
    "estado": "BAHIA",
    "pais": "Brasil",
    "municipio_id": "2911105",
    "estado_id": "29",
    "pais_id": "33",
    "numero_dias_sem_chuva": "",
    "precipitacao": "",
    "risco_fogo": "",
    "bioma": "Cerrado",
    "frp": ""
  },
  {
    "id": "d29ae8ab-3725-375a-8f15-3d84bd3c5b72",
    "lat": " -19.778500",
    "lon": " -42.013199",
    "data_hora_gmt": "2025-02-19 00:28:00",
    "satelite": "METOP-B",
    "municipio": "PIEDADE DE CARATINGA",
    "estado": "MINAS GERAIS",
    "pais": "Brasil",
    "municipio_id": "3150158",
    "estado_id": "31",
    "pais_id": "33",
    "numero_dias_sem_chuva": "",
    "precipitacao": "",
    "risco_fogo": "",
    "bioma": "Mata Atlântica",
    "frp": ""
  },
  {
    "id": "e12792e6-f8b3-31d7-8250-efbb7899d851",
    "lat": "  -3.270800",
    "lon": " -42.370201",
    "data_hora_gmt": "2025-02-19 00:28:00",
    "satelite": "METOP-B",
    "municipio": "SÃO BERNARDO",
    "estado": "MARANHÃO",
    "pais": "Brasil",
    "municipio_id": "2110609",
    "estado_id": "21",
    "pais_id": "33",
    "numero_dias_sem_chuva": "",
    "precipitacao": "",
    "risco_fogo": "",
    "bioma": "Cerrado",
    "frp": ""
  },
  {
    "id": "256676e0-97e3-351b-934c-e9d075053c8e",
    "lat": " -19.537001",
    "lon": " -45.907101",
    "data_hora_gmt": "2025-02-19 00:28:00",
    "satelite": "METOP-B",
    "municipio": "SANTA ROSA DA SERRA",
    "estado": "MINAS GERAIS",
    "pais": "Brasil",
    "municipio_id": "3159704",
    "estado_id": "31",
    "pais_id": "33",
    "numero_dias_sem_chuva": "",
    "precipitacao": "",
    "risco_fogo": "",
    "bioma": "Cerrado",
    "frp": ""
  },
  {
    "id": "121c7c9e-de53-30c9-bfbf-ae3b6c8ff37f",
    "lat": " -13.799500",
    "lon": " -41.681900",
    "data_hora_gmt": "2025-02-19 00:28:00",
    "satelite": "METOP-B",
    "municipio": "DOM BASÍLIO",
    "estado": "BAHIA",
    "pais": "Brasil",
    "municipio_id": "2910107",
    "estado_id": "29",
    "pais_id": "33",
    "numero_dias_sem_chuva": "",
    "precipitacao": "",
    "risco_fogo": "",
    "bioma": "Caatinga",
    "frp": ""
  },
  {
    "id": "553a24d7-c865-3ea7-b07d-4e088ca08875",
    "lat": " -13.793200",
    "lon": " -41.697899",
    "data_hora_gmt": "2025-02-19 00:28:00",
    "satelite": "METOP-B",
    "municipio": "DOM BASÍLIO",
    "estado": "BAHIA",
    "pais": "Brasil",
    "municipio_id": "2910107",
    "estado_id": "29",
    "pais_id": "33",
    "numero_dias_sem_chuva": "",
    "precipitacao": "",
    "risco_fogo": "",
    "bioma": "Caatinga",
    "frp": ""
  },
  {
    "id": "d356473b-cd78-3f6b-9328-a4bbb014a666",
    "lat": " -22.677500",
    "lon": " -42.848400",
    "data_hora_gmt": "2025-02-19 00:28:00",
    "satelite": "METOP-B",
    "municipio": "ITABORAÍ",
    "estado": "RIO DE JANEIRO",
    "pais": "Brasil",
    "municipio_id": "3301900",
    "estado_id": "33",
    "pais_id": "33",
    "numero_dias_sem_chuva": "",
    "precipitacao": "",
    "risco_fogo": "",
    "bioma": "Mata Atlântica",
    "frp": ""
  },
  {
    "id": "1944e3df-a8f2-3880-a7e6-e7b1a1f234d4",
    "lat": " -19.535299",
    "lon": " -45.899601",
    "data_hora_gmt": "2025-02-19 00:28:00",
    "satelite": "METOP-B",
    "municipio": "ESTRELA DO INDAIÁ",
    "estado": "MINAS GERAIS",
    "pais": "Brasil",
    "municipio_id": "3124708",
    "estado_id": "31",
    "pais_id": "33",
    "numero_dias_sem_chuva": "",
    "precipitacao": "",
    "risco_fogo": "",
    "bioma": "Cerrado",
    "frp": ""
  },
  {
    "id": "837bab69-45d1-346c-b9bb-b9fbfe50ee57",
    "lat": " -10.652600",
    "lon": " -44.488098",
    "data_hora_gmt": "2025-02-19 00:28:00",
    "satelite": "METOP-B",
    "municipio": "SANTA RITA DE CÁSSIA",
    "estado": "BAHIA",
    "pais": "Brasil",
    "municipio_id": "2928406",
    "estado_id": "29",
    "pais_id": "33",
    "numero_dias_sem_chuva": "",
    "precipitacao": "",
    "risco_fogo": "",
    "bioma": "Cerrado",
    "frp": ""
  },
  {
    "id": "32ef9b8d-6855-3bf3-979c-b4a850514ebf",
    "lat": " -10.650200",
    "lon": " -44.478001",
    "data_hora_gmt": "2025-02-19 00:28:00",
    "satelite": "METOP-B",
    "municipio": "SANTA RITA DE CÁSSIA",
    "estado": "BAHIA",
    "pais": "Brasil",
    "municipio_id": "2928406",
    "estado_id": "29",
    "pais_id": "33",
    "numero_dias_sem_chuva": "",
    "precipitacao": "",
    "risco_fogo": "",
    "bioma": "Cerrado",
    "frp": ""
  },
  {
    "id": "aa41ce42-0c3d-3bd4-9db7-bdf8a832f2e7",
    "lat": "  -1.581000",
    "lon": " -54.518902",
    "data_hora_gmt": "2025-02-19 00:28:00",
    "satelite": "METOP-B",
    "municipio": "ALENQUER",
    "estado": "PARÁ",
    "pais": "Brasil",
    "municipio_id": "1500404",
    "estado_id": "15",
    "pais_id": "33",
    "numero_dias_sem_chuva": "",
    "precipitacao": "",
    "risco_fogo": "",
    "bioma": "Amazônia",
    "frp": ""
  },
  {
    "id": "45e621e1-8e1f-36dc-9783-2e2437a2ee5b",
    "lat": " -11.035600",
    "lon": " -45.055901",
    "data_hora_gmt": "2025-02-19 00:28:00",
    "satelite": "METOP-B",
    "municipio": "FORMOSA DO RIO PRETO",
    "estado": "BAHIA",
    "pais": "Brasil",
    "municipio_id": "2911105",
    "estado_id": "29",
    "pais_id": "33",
    "numero_dias_sem_chuva": "",
    "precipitacao": "",
    "risco_fogo": "",
    "bioma": "Cerrado",
    "frp": ""
  },
  {
    "id": "ca73ccba-07e0-35fe-9a04-6551c28be79a",
    "lat": " -15.811400",
    "lon": " -42.103700",
    "data_hora_gmt": "2025-02-19 01:00:00",
    "satelite": "GOES-16",
    "municipio": "TAIOBEIRAS",
    "estado": "MINAS GERAIS",
    "pais": "Brasil",
    "municipio_id": "3168002",
    "estado_id": "31",
    "pais_id": "33",
    "numero_dias_sem_chuva": "",
    "precipitacao": "",
    "risco_fogo": "",
    "bioma": "Cerrado",
    "frp": "54.6"
  },
  {
    "id": "16524e7b-8d6c-3436-b624-4a8c9831bb3f",
    "lat": "   2.629600",
    "lon": " -61.138100",
    "data_hora_gmt": "2025-02-19 01:22:00",
    "satelite": "METOP-C",
    "municipio": "MUCAJAÍ",
    "estado": "RORAIMA",
    "pais": "Brasil",
    "municipio_id": "1400308",
    "estado_id": "14",
    "pais_id": "33",
    "numero_dias_sem_chuva": "",
    "precipitacao": "",
    "risco_fogo": "",
    "bioma": "Amazônia",
    "frp": ""
  },
  {
    "id": "6940b38a-0a5b-34bb-8b71-6d4a4ec8f0a3",
    "lat": "   2.632700",
    "lon": " -61.124500",
    "data_hora_gmt": "2025-02-19 01:22:00",
    "satelite": "METOP-C",
    "municipio": "MUCAJAÍ",
    "estado": "RORAIMA",
    "pais": "Brasil",
    "municipio_id": "1400308",
    "estado_id": "14",
    "pais_id": "33",
    "numero_dias_sem_chuva": "",
    "precipitacao": "",
    "risco_fogo": "",
    "bioma": "Amazônia",
    "frp": ""
  },
  {
    "id": "96454ee2-58e4-3055-ac04-af1803ff68d8",
    "lat": "   2.631100",
    "lon": " -61.131302",
    "data_hora_gmt": "2025-02-19 01:22:00",
    "satelite": "METOP-C",
    "municipio": "MUCAJAÍ",
    "estado": "RORAIMA",
    "pais": "Brasil",
    "municipio_id": "1400308",
    "estado_id": "14",
    "pais_id": "33",
    "numero_dias_sem_chuva": "",
    "precipitacao": "",
    "risco_fogo": "",
    "bioma": "Amazônia",
    "frp": ""
  }
]