[
  {
    "id": "a049559f-397f-305c-912f-d8cd71ae4119",
    "lat": " -11.853400",
    "lon": " -57.358200",
    "data_hora_gmt": "2026-01-11 00:00:00",
    "satelite": "GOES-19",
    "municipio": "NOVA MARINGÁ",
    "estado": "MATO GROSSO",
    "pais": "Brasil",
    "municipio_id": "5108907",
    "estado_id": "51",
    "pais_id": "33",
    "numero_dias_sem_chuva": "",
    "precipitacao": "",
    "risco_fogo": "",
    "bioma": "Amazônia",
    "frp": "129.5"
  },
  {
    "id": "10bd853a-9311-337b-aa5b-3f7e1955d19f",
    "lat": " -12.413300",
    "lon": " -58.049000",
    "data_hora_gmt": "2026-01-11 00:00:00",
    "satelite": "GOES-19",
    "municipio": "BRASNORTE",
    "estado": "MATO GROSSO",
    "pais": "Brasil",
    "municipio_id": "5101902",
    "estado_id": "51",
    "pais_id": "33",
    "numero_dias_sem_chuva": "",
    "precipitacao": "",
    "risco_fogo": "",
    "bioma": "Cerrado",
    "frp": "117.0"
  },
  {
    "id": "f8576fe7-a9a6-3dc5-9d35-69d93437f9a2",
    "lat": " -18.832000",
    "lon": " -51.609900",
    "data_hora_gmt": "2026-01-11 00:00:00",
    "satelite": "GOES-19",
    "municipio": "ITAJÁ",
    "estado": "GOIÁS",
    "pais": "Brasil",
    "municipio_id": "5210802",
    "estado_id": "52",
    "pais_id": "33",
    "numero_dias_sem_chuva": "",
    "precipitacao": "",
    "risco_fogo": "",
    "bioma": "Cerrado",
    "frp": "90.4"
  },
  {
    "id": "ae5083f2-26e2-3a23-96e4-d927d490ca02",
    "lat": " -18.811900",
    "lon": " -51.613400",
    "data_hora_gmt": "2026-01-11 00:00:00",
    "satelite": "GOES-19",
    "municipio": "ITAJÁ",
    "estado": "GOIÁS",
    "pais": "Brasil",
    "municipio_id": "5210802",
    "estado_id": "52",
    "pais_id": "33",
    "numero_dias_sem_chuva": "",
    "precipitacao": "",
    "risco_fogo": "",
    "bioma": "Cerrado",
    "frp": "91.2"
  },
  {
    "id": "435a1281-3345-31e8-b1cb-b25f74f8cddd",
    "lat": " -11.853200",
    "lon": " -57.378100",
    "data_hora_gmt": "2026-01-11 00:00:00",
    "satelite": "GOES-19",
    "municipio": "NOVA MARINGÁ",
    "estado": "MATO GROSSO",
    "pais": "Brasil",
    "municipio_id": "5108907",
    "estado_id": "51",
    "pais_id": "33",
    "numero_dias_sem_chuva": "",
    "precipitacao": "",
    "risco_fogo": "",
    "bioma": "Amazônia",
    "frp": "130.5"
  },
  {
    "id": "22fa614a-c1a8-34f4-8444-6a9534c748d9",
    "lat": " -12.394300",
    "lon": " -58.050600",
    "data_hora_gmt": "2026-01-11 00:00:00",
    "satelite": "GOES-19",
    "municipio": "BRASNORTE",
    "estado": "MATO GROSSO",
    "pais": "Brasil",
    "municipio_id": "5101902",
    "estado_id": "51",
    "pais_id": "33",
    "numero_dias_sem_chuva": "",
    "precipitacao": "",
    "risco_fogo": "",
    "bioma": "Cerrado",
    "frp": "103.2"
  },
  {
    "id": "a250fcf9-8122-3ec2-8cd3-bc0bb20809b0",
    "lat": " -12.413500",
    "lon": " -58.029200",
    "data_hora_gmt": "2026-01-11 00:00:00",
    "satelite": "GOES-19",
    "municipio": "BRASNORTE",
    "estado": "MATO GROSSO",
    "pais": "Brasil",
    "municipio_id": "5101902",
    "estado_id": "51",
    "pais_id": "33",
    "numero_dias_sem_chuva": "",
    "precipitacao": "",
    "risco_fogo": "",
    "bioma": "Cerrado",
    "frp": "78.3"
  },
  {
    "id": "a9023c42-00c2-3fd7-a66b-3f22f5158f13",
    "lat": " -12.394600",
    "lon": " -58.030700",
    "data_hora_gmt": "2026-01-11 00:00:00",
    "satelite": "GOES-19",
    "municipio": "BRASNORTE",
    "estado": "MATO GROSSO",
    "pais": "Brasil",
    "municipio_id": "5101902",
    "estado_id": "51",
    "pais_id": "33",
    "numero_dias_sem_chuva": "",
    "precipitacao": "",
    "risco_fogo": "",
    "bioma": "Cerrado",
    "frp": "67.1"
  },
  {
    "id": "59fd9962-0f71-30ef-ae80-388fbd9a6e56",
    "lat": " -11.872300",
    "lon": " -57.356600",
    "data_hora_gmt": "2026-01-11 00:10:00",
    "satelite": "GOES-19",
    "municipio": "NOVA MARINGÁ",
    "estado": "MATO GROSSO",
    "pais": "Brasil",
    "municipio_id": "5108907",
    "estado_id": "51",
    "pais_id": "33",
    "numero_dias_sem_chuva": "",
    "precipitacao": "",
    "risco_fogo": "",
    "bioma": "Amazônia",
    "frp": "71.6"
  },
  {
    "id": "612a194c-c6d7-38b9-b92d-aa325e7f6092",
    "lat": " -12.904100",
    "lon": " -52.515000",
    "data_hora_gmt": "2026-01-11 00:10:00",
    "satelite": "GOES-19",
    "municipio": "CANARANA",
    "estado": "MATO GROSSO",
    "pais": "Brasil",
    "municipio_id": "5102702",
    "estado_id": "51",
    "pais_id": "33",
    "numero_dias_sem_chuva": "",
    "precipitacao": "",
    "risco_fogo": "",
    "bioma": "Amazônia",
    "frp": "58.8"
  },
  {
    "id": "49d9f2bf-d369-3e8b-afc5-afb6a8e3ba16",
    "lat": " -18.811900",
    "lon": " -51.613400",
    "data_hora_gmt": "2026-01-11 00:10:00",
    "satelite": "GOES-19",
    "municipio": "ITAJÁ",
    "estado": "GOIÁS",
    "pais": "Brasil",
    "municipio_id": "5210802",
    "estado_id": "52",
    "pais_id": "33",
    "numero_dias_sem_chuva": "",
    "precipitacao": "",
    "risco_fogo": "",
    "bioma": "Cerrado",
    "frp": "89.1"
  },
  {
    "id": "a4bc8fba-759c-3802-85c0-21fdb4d110fa",
    "lat": " -11.853400",
    "lon": " -57.358200",
    "data_hora_gmt": "2026-01-11 00:10:00",
    "satelite": "GOES-19",
    "municipio": "NOVA MARINGÁ",
    "estado": "MATO GROSSO",
    "pais": "Brasil",
    "municipio_id": "5108907",
    "estado_id": "51",
    "pais_id": "33",
    "numero_dias_sem_chuva": "",
    "precipitacao": "",
    "risco_fogo": "",
    "bioma": "Amazônia",
    "frp": "112.1"
  },
  {
    "id": "77ff0506-5ad7-3bb5-8719-dcfbafce82d9",
    "lat": " -12.413500",
    "lon": " -58.029200",
    "data_hora_gmt": "2026-01-11 00:10:00",
    "satelite": "GOES-19",
    "municipio": "BRASNORTE",
    "estado": "MATO GROSSO",
    "pais": "Brasil",
    "municipio_id": "5101902",
    "estado_id": "51",
    "pais_id": "33",
    "numero_dias_sem_chuva": "",
    "precipitacao": "",
    "risco_fogo": "",
    "bioma": "Cerrado",
    "frp": "77.3"
  },
  {
    "id": "5253cc4e-d451-3b58-adfb-bd56d4f2fec1",
    "lat": " -11.853200",
    "lon": " -57.378100",
    "data_hora_gmt": "2026-01-11 00:10:00",
    "satelite": "GOES-19",
    "municipio": "NOVA MARINGÁ",
    "estado": "MATO GROSSO",
    "pais": "Brasil",
    "municipio_id": "5108907",
    "estado_id": "51",
    "pais_id": "33",
    "numero_dias_sem_chuva": "",
    "precipitacao": "",
    "risco_fogo": "",
    "bioma": "Amazônia",
    "frp": "144.2"
  },
  {
    "id": "3e988e01-357c-3660-b016-702b24b05290",
    "lat": " -18.832000",
    "lon": " -51.609900",
    "data_hora_gmt": "2026-01-11 00:10:00",
    "satelite": "GOES-19",
    "municipio": "ITAJÁ",
    "estado": "GOIÁS",
    "pais": "Brasil",
    "municipio_id": "5210802",
    "estado_id": "52",
    "pais_id": "33",
    "numero_dias_sem_chuva": "",
    "precipitacao": "",
    "risco_fogo": "",
    "bioma": "Cerrado",
    "frp": "71.9"
  },
  {
    "id": "6bb5d830-1494-3fe3-a8ac-e8e94ef80842",
    "lat": " -12.413300",
    "lon": " -58.049000",
    "data_hora_gmt": "2026-01-11 00:10:00",
    "satelite": "GOES-19",
    "municipio": "BRASNORTE",
    "estado": "MATO GROSSO",
    "pais": "Brasil",
    "municipio_id": "5101902",
    "estado_id": "51",
    "pais_id": "33",
    "numero_dias_sem_chuva": "",
    "precipitacao": "",
    "risco_fogo": "",
    "bioma": "Cerrado",
    "frp": "108.9"
  },
  {
    "id": "2ff81777-ea72-3c0a-9030-ac791e0f9206",
    "lat": " -11.872100",
    "lon": " -57.376600",
    "data_hora_gmt": "2026-01-11 00:10:00",
    "satelite": "GOES-19",
    "municipio": "NOVA MARINGÁ",
    "estado": "MATO GROSSO",
    "pais": "Brasil",
    "municipio_id": "5108907",
    "estado_id": "51",
    "pais_id": "33",
    "numero_dias_sem_chuva": "",
    "precipitacao": "",
    "risco_fogo": "",
    "bioma": "Amazônia",
    "frp": "85.8"
  },
  {
    "id": "3bac73d2-5051-30e2-a2bd-07112dafa6dd",
    "lat": " -12.394300",
    "lon": " -58.050600",
    "data_hora_gmt": "2026-01-11 00:10:00",
    "satelite": "GOES-19",
    "municipio": "BRASNORTE",
    "estado": "MATO GROSSO",
    "pais": "Brasil",
    "municipio_id": "5101902",
    "estado_id": "51",
    "pais_id": "33",
    "numero_dias_sem_chuva": "",
    "precipitacao": "",
    "risco_fogo": "",
    "bioma": "Cerrado",
    "frp": "104.0"
  },
  {
    "id": "afb1a169-5912-30d6-91b3-b22092cc3afe",
    "lat": " -12.394600",
    "lon": " -58.030700",
    "data_hora_gmt": "2026-01-11 00:10:00",
    "satelite": "GOES-19",
    "municipio": "BRASNORTE",
    "estado": "MATO GROSSO",
    "pais": "Brasil",
    "municipio_id": "5101902",
    "estado_id": "51",
    "pais_id": "33",
    "numero_dias_sem_chuva": "",
    "precipitacao": "",
    "risco_fogo": "",
    "bioma": "Cerrado",
    "frp": "69.9"
  },
  {
    "id": "acc11a4e-2d28-35cb-945d-dec9981841b9",
    "lat": " -11.853400",
    "lon": " -57.358200",
    "data_hora_gmt": "2026-01-11 00:20:00",
    "satelite": "GOES-19",
    "municipio": "NOVA MARINGÁ",
    "estado": "MATO GROSSO",
    "pais": "Brasil",
    "municipio_id": "5108907",
    "estado_id": "51",
    "pais_id": "33",
    "numero_dias_sem_chuva": "",
    "precipitacao": "",
    "risco_fogo": "",
    "bioma": "Amazônia",
    "frp": "115.4"
  },
  {
    "id": "9e98cf88-5755-305e-a0f4-9ab52b86d047",
    "lat": " -12.413500",
    "lon": " -58.029200",
    "data_hora_gmt": "2026-01-11 00:20:00",
    "satelite": "GOES-19",
    "municipio": "BRASNORTE",
    "estado": "MATO GROSSO",
    "pais": "Brasil",
    "municipio_id": "5101902",
    "estado_id": "51",
    "pais_id": "33",
    "numero_dias_sem_chuva": "",
    "precipitacao": "",
    "risco_fogo": "",
    "bioma": "Cerrado",
    "frp": "62.1"
  },
  {
    "id": "18ed792a-bfe5-3668-b3eb-fbe276302214",
    "lat": " -11.872300",
    "lon": " -57.356600",
    "data_hora_gmt": "2026-01-11 00:20:00",
    "satelite": "GOES-19",
    "municipio": "NOVA MARINGÁ",
    "estado": "MATO GROSSO",
    "pais": "Brasil",
    "municipio_id": "5108907",
    "estado_id": "51",
    "pais_id": "33",
    "numero_dias_sem_chuva": "",
    "precipitacao": "",
    "risco_fogo": "",
    "bioma": "Amazônia",
    "frp": "57.8"
  },
  {
    "id": "2dadd486-7141-31e4-9860-390cf0da9099",
    "lat": " -12.394300",
    "lon": " -58.050600",
    "data_hora_gmt": "2026-01-11 00:20:00",
    "satelite": "GOES-19",
    "municipio": "BRASNORTE",
    "estado": "MATO GROSSO",
    "pais": "Brasil",
    "municipio_id": "5101902",
    "estado_id": "51",
    "pais_id": "33",
    "numero_dias_sem_chuva": "",
    "precipitacao": "",
    "risco_fogo": "",
    "bioma": "Cerrado",
    "frp": "107.2"
  },
  {
    "id": "9cc9c6e7-277a-349a-9b58-012a7f6a60d2",
    "lat": " -11.872100",
    "lon": " -57.376600",
    "data_hora_gmt": "2026-01-11 00:20:00",
    "satelite": "GOES-19",
    "municipio": "NOVA MARINGÁ",
    "estado": "MATO GROSSO",
    "pais": "Brasil",
    "municipio_id": "5108907",
    "estado_id": "51",
    "pais_id": "33",
    "numero_dias_sem_chuva": "",
    "precipitacao": "",
    "risco_fogo": "",
    "bioma": "Amazônia",
    "frp": "67.3"
  },
  {
    "id": "1b8916fb-8864-3c0c-b876-07c69f04d0c3",
    "lat": " -12.904100",
    "lon": " -52.515000",
    "data_hora_gmt": "2026-01-11 00:20:00",
    "satelite": "GOES-19",
    "municipio": "CANARANA",
    "estado": "MATO GROSSO",
    "pais": "Brasil",
    "municipio_id": "5102702",
    "estado_id": "51",
    "pais_id": "33",
    "numero_dias_sem_chuva": "",
    "precipitacao": "",
    "risco_fogo": "",
    "bioma": "Amazônia",
    "frp": "56.8"
  },
  {
    "id": "df67a13d-71cb-36c8-90d7-ce11c3767be0",
    "lat": " -11.853200",
    "lon": " -57.378100",
    "data_hora_gmt": "2026-01-11 00:20:00",
    "satelite": "GOES-19",
    "municipio": "NOVA MARINGÁ",
    "estado": "MATO GROSSO",
    "pais": "Brasil",
    "municipio_id": "5108907",
    "estado_id": "51",
    "pais_id": "33",
    "numero_dias_sem_chuva": "",
    "precipitacao": "",
    "risco_fogo": "",
    "bioma": "Amazônia",
    "frp": "127.3"
  },
  {
    "id": "cf93e45c-48a7-3056-a815-4512616b7650",
    "lat": " -12.903800",
    "lon": " -52.536000",
    "data_hora_gmt": "2026-01-11 00:20:00",
    "satelite": "GOES-19",
    "municipio": "CANARANA",
    "estado": "MATO GROSSO",
    "pais": "Brasil",
    "municipio_id": "5102702",
    "estado_id": "51",
    "pais_id": "33",
    "numero_dias_sem_chuva": "",
    "precipitacao": "",
    "risco_fogo": "",
    "bioma": "Amazônia",
    "frp": "59.8"
  },
  {
    "id": "59a100d0-6003-3b5e-b926-dedecda9b0ae",
    "lat": " -12.413300",
    "lon": " -58.049000",
    "data_hora_gmt": "2026-01-11 00:20:00",
    "satelite": "GOES-19",
    "municipio": "BRASNORTE",
    "estado": "MATO GROSSO",
    "pais": "Brasil",
    "municipio_id": "5101902",
    "estado_id": "51",
    "pais_id": "33",
    "numero_dias_sem_chuva": "",
    "precipitacao": "",
    "risco_fogo": "",
    "bioma": "Cerrado",
    "frp": "87.5"
  },
  {
    "id": "fdb44d86-7388-3edb-80e9-156c9f289f1f",
    "lat": " -12.394600",
    "lon": " -58.030700",
    "data_hora_gmt": "2026-01-11 00:20:00",
    "satelite": "GOES-19",
    "municipio": "BRASNORTE",
    "estado": "MATO GROSSO",
    "pais": "Brasil",
    "municipio_id": "5101902",
    "estado_id": "51",
    "pais_id": "33",
    "numero_dias_sem_chuva": "",
    "precipitacao": "",
    "risco_fogo": "",
    "bioma": "Cerrado",
    "frp": "71.3"
  },
  {
    "id": "12c9c253-784e-31e0-a3f2-036d4d6fecf2",
    "lat": " -12.904100",
    "lon": " -52.515000",
    "data_hora_gmt": "2026-01-11 00:30:00",
    "satelite": "GOES-19",
    "municipio": "CANARANA",
    "estado": "MATO GROSSO",
    "pais": "Brasil",
    "municipio_id": "5102702",
    "estado_id": "51",
    "pais_id": "33",
    "numero_dias_sem_chuva": "",
    "precipitacao": "",
    "risco_fogo": "",
    "bioma": "Amazônia",
    "frp": "57.7"
  },
  {
    "id": "94060019-f494-31c4-9025-37f537b76067",
    "lat": " -12.394300",
    "lon": " -58.050600",
    "data_hora_gmt": "2026-01-11 00:30:00",
    "satelite": "GOES-19",
    "municipio": "BRASNORTE",
    "estado": "MATO GROSSO",
    "pais": "Brasil",
    "municipio_id": "5101902",
    "estado_id": "51",
    "pais_id": "33",
    "numero_dias_sem_chuva": "",
    "precipitacao": "",
    "risco_fogo": "",
    "bioma": "Cerrado",
    "frp": "65.3"
  },
  {
    "id": "aadf32ce-7e2a-3932-8182-9f399cc89282",
    "lat": " -11.853200",
    "lon": " -57.378100",
    "data_hora_gmt": "2026-01-11 00:30:00",
    "satelite": "GOES-19",
    "municipio": "NOVA MARINGÁ",
    "estado": "MATO GROSSO",
    "pais": "Brasil",
    "municipio_id": "5108907",
    "estado_id": "51",
    "pais_id": "33",
    "numero_dias_sem_chuva": "",
    "precipitacao": "",
    "risco_fogo": "",
    "bioma": "Amazônia",
    "frp": "86.9"
  },
  {
    "id": "7a3cccf4-a82f-3483-936e-7df107d3ebd6",
    "lat": " -11.872300",
    "lon": " -57.356600",
    "data_hora_gmt": "2026-01-11 00:30:00",
    "satelite": "GOES-19",
    "municipio": "NOVA MARINGÁ",
    "estado": "MATO GROSSO",
    "pais": "Brasil",
    "municipio_id": "5108907",
    "estado_id": "51",
    "pais_id": "33",
    "numero_dias_sem_chuva": "",
    "precipitacao": "",
    "risco_fogo": "",
    "bioma": "Amazônia",
    "frp": "63.7"
  },
  {
    "id": "a343a4b4-0394-3dbb-b098-8f049812946c",
    "lat": " -11.872100",
    "lon": " -57.376600",
    "data_hora_gmt": "2026-01-11 00:30:00",
    "satelite": "GOES-19",
    "municipio": "NOVA MARINGÁ",
    "estado": "MATO GROSSO",
    "pais": "Brasil",
    "municipio_id": "5108907",
    "estado_id": "51",
    "pais_id": "33",
    "numero_dias_sem_chuva": "",
    "precipitacao": "",
    "risco_fogo": "",
    "bioma": "Amazônia",
    "frp": "64.3"
  },
  {
    "id": "8d485f71-2a52-3ec6-ac12-d0f6628514dd",
    "lat": " -12.903800",
    "lon": " -52.536000",
    "data_hora_gmt": "2026-01-11 00:30:00",
    "satelite": "GOES-19",
    "municipio": "CANARANA",
    "estado": "MATO GROSSO",
    "pais": "Brasil",
    "municipio_id": "5102702",
    "estado_id": "51",
    "pais_id": "33",
    "numero_dias_sem_chuva": "",
    "precipitacao": "",
    "risco_fogo": "",
    "bioma": "Amazônia",
    "frp": "64.0"
  },
  {
    "id": "d5a4df61-d72f-3465-b3c9-ee3dea73bdc4",
    "lat": " -20.235600",
    "lon": " -46.468500",
    "data_hora_gmt": "2026-01-11 00:30:00",
    "satelite": "GOES-19",
    "municipio": "SÃO ROQUE DE MINAS",
    "estado": "MINAS GERAIS",
    "pais": "Brasil",
    "municipio_id": "3164308",
    "estado_id": "31",
    "pais_id": "33",
    "numero_dias_sem_chuva": "",
    "precipitacao": "",
    "risco_fogo": "",
    "bioma": "Cerrado",
    "frp": "51.7"
  },
  {
    "id": "37d937b0-6fe0-3cd3-9b20-4dc3d720deba",
    "lat": " -11.853400",
    "lon": " -57.358200",
    "data_hora_gmt": "2026-01-11 00:30:00",
    "satelite": "GOES-19",
    "municipio": "NOVA MARINGÁ",
    "estado": "MATO GROSSO",
    "pais": "Brasil",
    "municipio_id": "5108907",
    "estado_id": "51",
    "pais_id": "33",
    "numero_dias_sem_chuva": "",
    "precipitacao": "",
    "risco_fogo": "",
    "bioma": "Amazônia",
    "frp": "86.1"
  },
  {
    "id": "12c57175-687b-3971-9beb-85038f06e1ae",
    "lat": "  -2.251200",
    "lon": " -47.958099",
    "data_hora_gmt": "2026-01-11 00:38:00",
    "satelite": "METOP-C",
    "municipio": "AURORA DO PARÁ",
    "estado": "PARÁ",
    "pais": "Brasil",
    "municipio_id": "1500958",
    "estado_id": "15",
    "pais_id": "33",
    "numero_dias_sem_chuva": "",
    "precipitacao": "",
    "risco_fogo": "",
    "bioma": "Amazônia",
    "frp": ""
  },
  {
    "id": "e08ce65d-8a65-3258-8d6b-125e33821d79",
    "lat": "   -.091100",
    "lon": " -51.266102",
    "data_hora_gmt": "2026-01-11 00:38:00",
    "satelite": "METOP-C",
    "municipio": "SANTANA",
    "estado": "AMAPÁ",
    "pais": "Brasil",
    "municipio_id": "1600600",
    "estado_id": "16",
    "pais_id": "33",
    "numero_dias_sem_chuva": "",
    "precipitacao": "",
    "risco_fogo": "",
    "bioma": "Amazônia",
    "frp": ""
  },
  {
    "id": "6cb42370-63ee-3734-886e-650f6c827273",
    "lat": "  -2.616600",
    "lon": " -43.089401",
    "data_hora_gmt": "2026-01-11 00:38:00",
    "satelite": "METOP-C",
    "municipio": "SANTO AMARO DO MARANHÃO",
    "estado": "MARANHÃO",
    "pais": "Brasil",
    "municipio_id": "2110278",
    "estado_id": "21",
    "pais_id": "33",
    "numero_dias_sem_chuva": "",
    "precipitacao": "",
    "risco_fogo": "",
    "bioma": "Cerrado",
    "frp": ""
  },
  {
    "id": "997dc3b2-833e-3916-923e-8b9869f0506e",
    "lat": "  -2.185900",
    "lon": " -52.007900",
    "data_hora_gmt": "2026-01-11 00:38:00",
    "satelite": "METOP-C",
    "municipio": "PORTO DE MOZ",
    "estado": "PARÁ",
    "pais": "Brasil",
    "municipio_id": "1505908",
    "estado_id": "15",
    "pais_id": "33",
    "numero_dias_sem_chuva": "",
    "precipitacao": "",
    "risco_fogo": "",
    "bioma": "Amazônia",
    "frp": ""
  },
  {
    "id": "998135a8-643a-3860-93b9-19ac299be59e",
    "lat": "   -.084700",
    "lon": " -51.283298",
    "data_hora_gmt": "2026-01-11 00:38:00",
    "satelite": "METOP-C",
    "municipio": "MAZAGÃO",
    "estado": "AMAPÁ",
    "pais": "Brasil",
    "municipio_id": "1600402",
    "estado_id": "16",
    "pais_id": "33",
    "numero_dias_sem_chuva": "",
    "precipitacao": "",
    "risco_fogo": "",
    "bioma": "Amazônia",
    "frp": ""
  },
  {
    "id": "0d604080-5f9e-3c73-858d-9f6df6e6cb38",
    "lat": "  -2.187900",
    "lon": " -52.016399",
    "data_hora_gmt": "2026-01-11 00:38:00",
    "satelite": "METOP-C",
    "municipio": "PORTO DE MOZ",
    "estado": "PARÁ",
    "pais": "Brasil",
    "municipio_id": "1505908",
    "estado_id": "15",
    "pais_id": "33",
    "numero_dias_sem_chuva": "",
    "precipitacao": "",
    "risco_fogo": "",
    "bioma": "Amazônia",
    "frp": ""
  },
  {
    "id": "99cdd838-9571-3315-b45c-381967e056c7",
    "lat": "  -2.697100",
    "lon": " -45.509602",
    "data_hora_gmt": "2026-01-11 00:38:00",
    "satelite": "METOP-C",
    "municipio": "SANTA HELENA",
    "estado": "MARANHÃO",
    "pais": "Brasil",
    "municipio_id": "2109809",
    "estado_id": "21",
    "pais_id": "33",
    "numero_dias_sem_chuva": "",
    "precipitacao": "",
    "risco_fogo": "",
    "bioma": "Amazônia",
    "frp": ""
  },
  {
    "id": "f78eb6cb-58ea-36c9-b07b-7913a7b37805",
    "lat": " -18.814400",
    "lon": " -51.599899",
    "data_hora_gmt": "2026-01-11 00:38:00",
    "satelite": "METOP-C",
    "municipio": "ITAJÁ",
    "estado": "GOIÁS",
    "pais": "Brasil",
    "municipio_id": "5210802",
    "estado_id": "52",
    "pais_id": "33",
    "numero_dias_sem_chuva": "",
    "precipitacao": "",
    "risco_fogo": "",
    "bioma": "Cerrado",
    "frp": ""
  },
  {
    "id": "41eba85d-8296-3965-984f-6f029cbd3ef2",
    "lat": " -20.231600",
    "lon": " -46.474899",
    "data_hora_gmt": "2026-01-11 00:38:00",
    "satelite": "METOP-C",
    "municipio": "SÃO ROQUE DE MINAS",
    "estado": "MINAS GERAIS",
    "pais": "Brasil",
    "municipio_id": "3164308",
    "estado_id": "31",
    "pais_id": "33",
    "numero_dias_sem_chuva": "",
    "precipitacao": "",
    "risco_fogo": "",
    "bioma": "Cerrado",
    "frp": ""
  },
  {
    "id": "bdc51285-78c4-3543-8ab3-41b9868b2001",
    "lat": " -22.595301",
    "lon": " -43.311298",
    "data_hora_gmt": "2026-01-11 00:38:00",
    "satelite": "METOP-C",
    "municipio": "DUQUE DE CAXIAS",
    "estado": "RIO DE JANEIRO",
    "pais": "Brasil",
    "municipio_id": "3301702",
    "estado_id": "33",
    "pais_id": "33",
    "numero_dias_sem_chuva": "",
    "precipitacao": "",
    "risco_fogo": "",
    "bioma": "Mata Atlântica",
    "frp": ""
  },
  {
    "id": "b968449a-4cc3-3de5-b3bd-bf0fca3325c4",
    "lat": "   -.274000",
    "lon": " -48.779499",
    "data_hora_gmt": "2026-01-11 00:38:00",
    "satelite": "METOP-C",
    "municipio": "SOURE",
    "estado": "PARÁ",
    "pais": "Brasil",
    "municipio_id": "1507904",
    "estado_id": "15",
    "pais_id": "33",
    "numero_dias_sem_chuva": "",
    "precipitacao": "",
    "risco_fogo": "",
    "bioma": "Amazônia",
    "frp": ""
  },
  {
    "id": "d6f29916-653a-3b3f-ad9a-f173a7aca7e9",
    "lat": "  -5.460800",
    "lon": " -45.286598",
    "data_hora_gmt": "2026-01-11 00:38:00",
    "satelite": "METOP-C",
    "municipio": "BARRA DO CORDA",
    "estado": "MARANHÃO",
    "pais": "Brasil",
    "municipio_id": "2101608",
    "estado_id": "21",
    "pais_id": "33",
    "numero_dias_sem_chuva": "",
    "precipitacao": "",
    "risco_fogo": "",
    "bioma": "Cerrado",
    "frp": ""
  },
  {
    "id": "67e04075-4ad6-392b-931f-c0928e91d19e",
    "lat": "  -2.195700",
    "lon": " -52.005699",
    "data_hora_gmt": "2026-01-11 00:38:00",
    "satelite": "METOP-C",
    "municipio": "PORTO DE MOZ",
    "estado": "PARÁ",
    "pais": "Brasil",
    "municipio_id": "1505908",
    "estado_id": "15",
    "pais_id": "33",
    "numero_dias_sem_chuva": "",
    "precipitacao": "",
    "risco_fogo": "",
    "bioma": "Amazônia",
    "frp": ""
  },
  {
    "id": "b200d385-3307-373e-92b6-8329e1dd2df1",
    "lat": " -18.816999",
    "lon": " -51.613899",
    "data_hora_gmt": "2026-01-11 00:38:00",
    "satelite": "METOP-C",
    "municipio": "ITAJÁ",
    "estado": "GOIÁS",
    "pais": "Brasil",
    "municipio_id": "5210802",
    "estado_id": "52",
    "pais_id": "33",
    "numero_dias_sem_chuva": "",
    "precipitacao": "",
    "risco_fogo": "",
    "bioma": "Cerrado",
    "frp": ""
  },
  {
    "id": "89dbcbc2-d059-3905-9d38-cdfc8b8d9c18",
    "lat": "  -3.554700",
    "lon": " -43.664501",
    "data_hora_gmt": "2026-01-11 00:38:00",
    "satelite": "METOP-C",
    "municipio": "NINA RODRIGUES",
    "estado": "MARANHÃO",
    "pais": "Brasil",
    "municipio_id": "2107209",
    "estado_id": "21",
    "pais_id": "33",
    "numero_dias_sem_chuva": "",
    "precipitacao": "",
    "risco_fogo": "",
    "bioma": "Cerrado",
    "frp": ""
  },
  {
    "id": "b87c2731-a5dc-3e3c-8e5b-aee00533b07b",
    "lat": " -20.233299",
    "lon": " -46.482700",
    "data_hora_gmt": "2026-01-11 00:38:00",
    "satelite": "METOP-C",
    "municipio": "SÃO ROQUE DE MINAS",
    "estado": "MINAS GERAIS",
    "pais": "Brasil",
    "municipio_id": "3164308",
    "estado_id": "31",
    "pais_id": "33",
    "numero_dias_sem_chuva": "",
    "precipitacao": "",
    "risco_fogo": "",
    "bioma": "Cerrado",
    "frp": ""
  },
  {
    "id": "1e07b324-ef71-37b7-a96b-0aa668501d24",
    "lat": "   -.094500",
    "lon": " -51.281200",
    "data_hora_gmt": "2026-01-11 00:38:00",
    "satelite": "METOP-C",
    "municipio": "MAZAGÃO",
    "estado": "AMAPÁ",
    "pais": "Brasil",
    "municipio_id": "1600402",
    "estado_id": "16",
    "pais_id": "33",
    "numero_dias_sem_chuva": "",
    "precipitacao": "",
    "risco_fogo": "",
    "bioma": "Amazônia",
    "frp": ""
  },
  {
    "id": "734ed57c-9594-357b-95aa-e2b8364f4508",
    "lat": "  -1.023800",
    "lon": " -47.687698",
    "data_hora_gmt": "2026-01-11 00:38:00",
    "satelite": "METOP-C",
    "municipio": "MARAPANIM",
    "estado": "PARÁ",
    "pais": "Brasil",
    "municipio_id": "1504406",
    "estado_id": "15",
    "pais_id": "33",
    "numero_dias_sem_chuva": "",
    "precipitacao": "",
    "risco_fogo": "",
    "bioma": "Amazônia",
    "frp": ""
  },
  {
    "id": "43489dfa-c93d-3415-a4cb-44a2f894fe10",
    "lat": "  -2.249600",
    "lon": " -47.951199",
    "data_hora_gmt": "2026-01-11 00:38:00",
    "satelite": "METOP-C",
    "municipio": "AURORA DO PARÁ",
    "estado": "PARÁ",
    "pais": "Brasil",
    "municipio_id": "1500958",
    "estado_id": "15",
    "pais_id": "33",
    "numero_dias_sem_chuva": "",
    "precipitacao": "",
    "risco_fogo": "",
    "bioma": "Amazônia",
    "frp": ""
  },
  {
    "id": "6c113763-0419-38d6-8922-b50636989905",
    "lat": "  -2.184000",
    "lon": " -51.999298",
    "data_hora_gmt": "2026-01-11 00:38:00",
    "satelite": "METOP-C",
    "municipio": "PORTO DE MOZ",
    "estado": "PARÁ",
    "pais": "Brasil",
    "municipio_id": "1505908",
    "estado_id": "15",
    "pais_id": "33",
    "numero_dias_sem_chuva": "",
    "precipitacao": "",
    "risco_fogo": "",
    "bioma": "Amazônia",
    "frp": ""
  },
  {
    "id": "998e368b-3ea8-3d78-9bef-e0542664646e",
    "lat": " -20.230000",
    "lon": " -46.466999",
    "data_hora_gmt": "2026-01-11 00:38:00",
    "satelite": "METOP-C",
    "municipio": "SÃO ROQUE DE MINAS",
    "estado": "MINAS GERAIS",
    "pais": "Brasil",
    "municipio_id": "3164308",
    "estado_id": "31",
    "pais_id": "33",
    "numero_dias_sem_chuva": "",
    "precipitacao": "",
    "risco_fogo": "",
    "bioma": "Cerrado",
    "frp": ""
  },
  {
    "id": "ff0a2e19-fb20-33b8-8efc-252362b7f43d",
    "lat": "  -3.552400",
    "lon": " -43.654598",
    "data_hora_gmt": "2026-01-11 00:38:00",
    "satelite": "METOP-C",
    "municipio": "NINA RODRIGUES",
    "estado": "MARANHÃO",
    "pais": "Brasil",
    "municipio_id": "2107209",
    "estado_id": "21",
    "pais_id": "33",
    "numero_dias_sem_chuva": "",
    "precipitacao": "",
    "risco_fogo": "",
    "bioma": "Cerrado",
    "frp": ""
  },
  {
    "id": "197b59ac-c215-37f7-845c-841831bc82d8",
    "lat": "  -2.699000",
    "lon": " -45.517601",
    "data_hora_gmt": "2026-01-11 00:38:00",
    "satelite": "METOP-C",
    "municipio": "SANTA HELENA",
    "estado": "MARANHÃO",
    "pais": "Brasil",
    "municipio_id": "2109809",
    "estado_id": "21",
    "pais_id": "33",
    "numero_dias_sem_chuva": "",
    "precipitacao": "",
    "risco_fogo": "",
    "bioma": "Amazônia",
    "frp": ""
  },
  {
    "id": "074b61d4-d27c-3ac3-a88e-4e098c8b0c1e",
    "lat": "   -.083000",
    "lon": " -51.275799",
    "data_hora_gmt": "2026-01-11 00:38:00",
    "satelite": "METOP-C",
    "municipio": "SANTANA",
    "estado": "AMAPÁ",
    "pais": "Brasil",
    "municipio_id": "1600600",
    "estado_id": "16",
    "pais_id": "33",
    "numero_dias_sem_chuva": "",
    "precipitacao": "",
    "risco_fogo": "",
    "bioma": "Amazônia",
    "frp": ""
  },
  {
    "id": "21a113ee-df83-348e-b88e-71d2bcc03a67",
    "lat": " -20.247999",
    "lon": " -46.504101",
    "data_hora_gmt": "2026-01-11 00:38:00",
    "satelite": "METOP-C",
    "municipio": "SÃO ROQUE DE MINAS",
    "estado": "MINAS GERAIS",
    "pais": "Brasil",
    "municipio_id": "3164308",
    "estado_id": "31",
    "pais_id": "33",
    "numero_dias_sem_chuva": "",
    "precipitacao": "",
    "risco_fogo": "",
    "bioma": "Cerrado",
    "frp": ""
  },
  {
    "id": "4e14a6a3-760a-3475-b76a-48f752949302",
    "lat": " -17.759899",
    "lon": " -43.427700",
    "data_hora_gmt": "2026-01-11 00:38:00",
    "satelite": "METOP-C",
    "municipio": "DIAMANTINA",
    "estado": "MINAS GERAIS",
    "pais": "Brasil",
    "municipio_id": "3121605",
    "estado_id": "31",
    "pais_id": "33",
    "numero_dias_sem_chuva": "",
    "precipitacao": "",
    "risco_fogo": "",
    "bioma": "Cerrado",
    "frp": ""
  },
  {
    "id": "8c463d05-4eaf-3b34-87d9-ea31694682fb",
    "lat": " -17.758200",
    "lon": " -43.420200",
    "data_hora_gmt": "2026-01-11 00:38:00",
    "satelite": "METOP-C",
    "municipio": "DIAMANTINA",
    "estado": "MINAS GERAIS",
    "pais": "Brasil",
    "municipio_id": "3121605",
    "estado_id": "31",
    "pais_id": "33",
    "numero_dias_sem_chuva": "",
    "precipitacao": "",
    "risco_fogo": "",
    "bioma": "Cerrado",
    "frp": ""
  },
  {
    "id": "6356ce9e-aae9-35ea-9f47-a169f4bd7506",
    "lat": " -11.077100",
    "lon": " -48.260700",
    "data_hora_gmt": "2026-01-11 00:38:00",
    "satelite": "METOP-C",
    "municipio": "SILVANÓPOLIS",
    "estado": "TOCANTINS",
    "pais": "Brasil",
    "municipio_id": "1720655",
    "estado_id": "17",
    "pais_id": "33",
    "numero_dias_sem_chuva": "",
    "precipitacao": "",
    "risco_fogo": "",
    "bioma": "Cerrado",
    "frp": ""
  },
  {
    "id": "38cbbc76-d2aa-37b8-8c0c-0c3e30c243c3",
    "lat": " -18.826799",
    "lon": " -51.612000",
    "data_hora_gmt": "2026-01-11 00:38:00",
    "satelite": "METOP-C",
    "municipio": "ITAJÁ",
    "estado": "GOIÁS",
    "pais": "Brasil",
    "municipio_id": "5210802",
    "estado_id": "52",
    "pais_id": "33",
    "numero_dias_sem_chuva": "",
    "precipitacao": "",
    "risco_fogo": "",
    "bioma": "Cerrado",
    "frp": ""
  },
  {
    "id": "9782fb2d-aadc-3caf-8435-a7e02bf96c24",
    "lat": "   -.275500",
    "lon": " -48.786301",
    "data_hora_gmt": "2026-01-11 00:38:00",
    "satelite": "METOP-C",
    "municipio": "SOURE",
    "estado": "PARÁ",
    "pais": "Brasil",
    "municipio_id": "1507904",
    "estado_id": "15",
    "pais_id": "33",
    "numero_dias_sem_chuva": "",
    "precipitacao": "",
    "risco_fogo": "",
    "bioma": "Amazônia",
    "frp": ""
  },
  {
    "id": "9a115200-fe9a-3828-9160-e92be785881d",
    "lat": "  -1.843300",
    "lon": " -54.302299",
    "data_hora_gmt": "2026-01-11 00:38:00",
    "satelite": "METOP-C",
    "municipio": "MONTE ALEGRE",
    "estado": "PARÁ",
    "pais": "Brasil",
    "municipio_id": "1504802",
    "estado_id": "15",
    "pais_id": "33",
    "numero_dias_sem_chuva": "",
    "precipitacao": "",
    "risco_fogo": "",
    "bioma": "Amazônia",
    "frp": ""
  },
  {
    "id": "6962587e-492f-378f-a85a-539272731c1a",
    "lat": " -11.854400",
    "lon": " -57.353199",
    "data_hora_gmt": "2026-01-11 00:38:00",
    "satelite": "METOP-C",
    "municipio": "NOVA MARINGÁ",
    "estado": "MATO GROSSO",
    "pais": "Brasil",
    "municipio_id": "5108907",
    "estado_id": "51",
    "pais_id": "33",
    "numero_dias_sem_chuva": "",
    "precipitacao": "",
    "risco_fogo": "",
    "bioma": "Amazônia",
    "frp": ""
  },
  {
    "id": "abc3a98b-48b0-3a4f-9f60-11a3dcf48708",
    "lat": "  -1.266000",
    "lon": " -45.739101",
    "data_hora_gmt": "2026-01-11 00:38:00",
    "satelite": "METOP-C",
    "municipio": "GODOFREDO VIANA",
    "estado": "MARANHÃO",
    "pais": "Brasil",
    "municipio_id": "2104305",
    "estado_id": "21",
    "pais_id": "33",
    "numero_dias_sem_chuva": "",
    "precipitacao": "",
    "risco_fogo": "",
    "bioma": "Amazônia",
    "frp": ""
  },
  {
    "id": "7206b3fb-fbf5-31f0-96f4-328fa0566d38",
    "lat": " -22.597000",
    "lon": " -43.318802",
    "data_hora_gmt": "2026-01-11 00:38:00",
    "satelite": "METOP-C",
    "municipio": "DUQUE DE CAXIAS",
    "estado": "RIO DE JANEIRO",
    "pais": "Brasil",
    "municipio_id": "3301702",
    "estado_id": "33",
    "pais_id": "33",
    "numero_dias_sem_chuva": "",
    "precipitacao": "",
    "risco_fogo": "",
    "bioma": "Mata Atlântica",
    "frp": ""
  },
  {
    "id": "80a97b94-e213-39e6-be08-49652e8ede79",
    "lat": "  -2.619200",
    "lon": " -43.100399",
    "data_hora_gmt": "2026-01-11 00:38:00",
    "satelite": "METOP-C",
    "municipio": "SANTO AMARO DO MARANHÃO",
    "estado": "MARANHÃO",
    "pais": "Brasil",
    "municipio_id": "2110278",
    "estado_id": "21",
    "pais_id": "33",
    "numero_dias_sem_chuva": "",
    "precipitacao": "",
    "risco_fogo": "",
    "bioma": "Cerrado",
    "frp": ""
  },
  {
    "id": "945ae3da-a839-3168-9e5b-5dac63d21a61",
    "lat": "  -2.708800",
    "lon": " -45.515400",
    "data_hora_gmt": "2026-01-11 00:38:00",
    "satelite": "METOP-C",
    "municipio": "SANTA HELENA",
    "estado": "MARANHÃO",
    "pais": "Brasil",
    "municipio_id": "2109809",
    "estado_id": "21",
    "pais_id": "33",
    "numero_dias_sem_chuva": "",
    "precipitacao": "",
    "risco_fogo": "",
    "bioma": "Amazônia",
    "frp": ""
  },
  {
    "id": "c566f61e-31cb-3436-bf6d-eec753f12842",
    "lat": "   -.092800",
    "lon": " -51.273602",
    "data_hora_gmt": "2026-01-11 00:38:00",
    "satelite": "METOP-C",
    "municipio": "MAZAGÃO",
    "estado": "AMAPÁ",
    "pais": "Brasil",
    "municipio_id": "1600402",
    "estado_id": "16",
    "pais_id": "33",
    "numero_dias_sem_chuva": "",
    "precipitacao": "",
    "risco_fogo": "",
    "bioma": "Amazônia",
    "frp": ""
  },
  {
    "id": "a381cfba-6d65-3ed2-bb5e-450480248ebc",
    "lat": "  -5.856300",
    "lon": " -44.947800",
    "data_hora_gmt": "2026-01-11 00:38:00",
    "satelite": "METOP-C",
    "municipio": "FERNANDO FALCÃO",
    "estado": "MARANHÃO",
    "pais": "Brasil",
    "municipio_id": "2104081",
    "estado_id": "21",
    "pais_id": "33",
    "numero_dias_sem_chuva": "",
    "precipitacao": "",
    "risco_fogo": "",
    "bioma": "Cerrado",
    "frp": ""
  },
  {
    "id": "e956945c-558f-3477-b425-6048c8dc3bd2",
    "lat": " -11.853400",
    "lon": " -57.358200",
    "data_hora_gmt": "2026-01-11 00:40:00",
    "satelite": "GOES-19",
    "municipio": "NOVA MARINGÁ",
    "estado": "MATO GROSSO",
    "pais": "Brasil",
    "municipio_id": "5108907",
    "estado_id": "51",
    "pais_id": "33",
    "numero_dias_sem_chuva": "",
    "precipitacao": "",
    "risco_fogo": "",
    "bioma": "Amazônia",
    "frp": "80.6"
  },
  {
    "id": "80879200-abd2-377a-82b2-a37eda684767",
    "lat": " -12.904100",
    "lon": " -52.515000",
    "data_hora_gmt": "2026-01-11 00:40:00",
    "satelite": "GOES-19",
    "municipio": "CANARANA",
    "estado": "MATO GROSSO",
    "pais": "Brasil",
    "municipio_id": "5102702",
    "estado_id": "51",
    "pais_id": "33",
    "numero_dias_sem_chuva": "",
    "precipitacao": "",
    "risco_fogo": "",
    "bioma": "Amazônia",
    "frp": "57.2"
  },
  {
    "id": "f399377e-e8b0-30ef-a5e6-85809e8456ee",
    "lat": " -12.903800",
    "lon": " -52.536000",
    "data_hora_gmt": "2026-01-11 00:40:00",
    "satelite": "GOES-19",
    "municipio": "CANARANA",
    "estado": "MATO GROSSO",
    "pais": "Brasil",
    "municipio_id": "5102702",
    "estado_id": "51",
    "pais_id": "33",
    "numero_dias_sem_chuva": "",
    "precipitacao": "",
    "risco_fogo": "",
    "bioma": "Amazônia",
    "frp": "59.4"
  },
  {
    "id": "c3bb0ef9-b1f6-382e-a8d4-f2659557a288",
    "lat": " -11.872100",
    "lon": " -57.376600",
    "data_hora_gmt": "2026-01-11 00:40:00",
    "satelite": "GOES-19",
    "municipio": "NOVA MARINGÁ",
    "estado": "MATO GROSSO",
    "pais": "Brasil",
    "municipio_id": "5108907",
    "estado_id": "51",
    "pais_id": "33",
    "numero_dias_sem_chuva": "",
    "precipitacao": "",
    "risco_fogo": "",
    "bioma": "Amazônia",
    "frp": "69.3"
  },
  {
    "id": "6126e1c9-6dc9-3209-b982-2f01d4316ee3",
    "lat": " -11.872300",
    "lon": " -57.356600",
    "data_hora_gmt": "2026-01-11 00:40:00",
    "satelite": "GOES-19",
    "municipio": "NOVA MARINGÁ",
    "estado": "MATO GROSSO",
    "pais": "Brasil",
    "municipio_id": "5108907",
    "estado_id": "51",
    "pais_id": "33",
    "numero_dias_sem_chuva": "",
    "precipitacao": "",
    "risco_fogo": "",
    "bioma": "Amazônia",
    "frp": "60.1"
  },
  {
    "id": "9d5963b3-7d6d-306a-a4d1-b0e5bc0dec1c",
    "lat": " -11.853200",
    "lon": " -57.378100",
    "data_hora_gmt": "2026-01-11 00:40:00",
    "satelite": "GOES-19",
    "municipio": "NOVA MARINGÁ",
    "estado": "MATO GROSSO",
    "pais": "Brasil",
    "municipio_id": "5108907",
    "estado_id": "51",
    "pais_id": "33",
    "numero_dias_sem_chuva": "",
    "precipitacao": "",
    "risco_fogo": "",
    "bioma": "Amazônia",
    "frp": "99.4"
  },
  {
    "id": "0b2c7ddb-4a5f-301b-93e0-a2383f402aa4",
    "lat": " -20.251370",
    "lon": " -46.512070",
    "data_hora_gmt": "2026-01-11 00:47:00",
    "satelite": "TERRA_M-M",
    "municipio": "SÃO ROQUE DE MINAS",
    "estado": "MINAS GERAIS",
    "pais": "Brasil",
    "municipio_id": "3164308",
    "estado_id": "31",
    "pais_id": "33",
    "numero_dias_sem_chuva": "",
    "precipitacao": "",
    "risco_fogo": "",
    "bioma": "Cerrado",
    "frp": "16.2"
  },
  {
    "id": "a453c7d7-5f66-3001-9ad1-c9658e0cef1f",
    "lat": " -20.229460",
    "lon": " -46.458480",
    "data_hora_gmt": "2026-01-11 00:47:00",
    "satelite": "TERRA_M-M",
    "municipio": "SÃO ROQUE DE MINAS",
    "estado": "MINAS GERAIS",
    "pais": "Brasil",
    "municipio_id": "3164308",
    "estado_id": "31",
    "pais_id": "33",
    "numero_dias_sem_chuva": "",
    "precipitacao": "",
    "risco_fogo": "",
    "bioma": "Cerrado",
    "frp": "16.9"
  },
  {
    "id": "05321657-3b64-315d-ae9f-b1b9c134cf2e",
    "lat": " -20.235620",
    "lon": " -46.470760",
    "data_hora_gmt": "2026-01-11 00:47:00",
    "satelite": "TERRA_M-M",
    "municipio": "SÃO ROQUE DE MINAS",
    "estado": "MINAS GERAIS",
    "pais": "Brasil",
    "municipio_id": "3164308",
    "estado_id": "31",
    "pais_id": "33",
    "numero_dias_sem_chuva": "",
    "precipitacao": "",
    "risco_fogo": "",
    "bioma": "Cerrado",
    "frp": "84.4"
  },
  {
    "id": "fbd78e6f-13dd-3f9c-9c3f-60c36a887282",
    "lat": " -20.239030",
    "lon": " -46.489570",
    "data_hora_gmt": "2026-01-11 00:47:00",
    "satelite": "TERRA_M-M",
    "municipio": "SÃO ROQUE DE MINAS",
    "estado": "MINAS GERAIS",
    "pais": "Brasil",
    "municipio_id": "3164308",
    "estado_id": "31",
    "pais_id": "33",
    "numero_dias_sem_chuva": "",
    "precipitacao": "",
    "risco_fogo": "",
    "bioma": "Cerrado",
    "frp": "24.2"
  },
  {
    "id": "224ff0b5-6e21-34cc-a3f7-c273b8cf95da",
    "lat": " -20.232710",
    "lon": " -46.477160",
    "data_hora_gmt": "2026-01-11 00:47:00",
    "satelite": "TERRA_M-M",
    "municipio": "SÃO ROQUE DE MINAS",
    "estado": "MINAS GERAIS",
    "pais": "Brasil",
    "municipio_id": "3164308",
    "estado_id": "31",
    "pais_id": "33",
    "numero_dias_sem_chuva": "",
    "precipitacao": "",
    "risco_fogo": "",
    "bioma": "Cerrado",
    "frp": "80.5"
  },
  {
    "id": "3fc0d2ad-7461-3d88-b2c1-200689f7d5e0",
    "lat": " -11.856900",
    "lon": " -57.382580",
    "data_hora_gmt": "2026-01-11 00:49:00",
    "satelite": "TERRA_M-M",
    "municipio": "NOVA MARINGÁ",
    "estado": "MATO GROSSO",
    "pais": "Brasil",
    "municipio_id": "5108907",
    "estado_id": "51",
    "pais_id": "33",
    "numero_dias_sem_chuva": "",
    "precipitacao": "",
    "risco_fogo": "",
    "bioma": "Amazônia",
    "frp": "23.3"
  },
  {
    "id": "73fb2c73-51b4-35a4-89b8-dfd79798e775",
    "lat": " -11.865150",
    "lon": " -57.370340",
    "data_hora_gmt": "2026-01-11 00:49:00",
    "satelite": "TERRA_M-M",
    "municipio": "NOVA MARINGÁ",
    "estado": "MATO GROSSO",
    "pais": "Brasil",
    "municipio_id": "5108907",
    "estado_id": "51",
    "pais_id": "33",
    "numero_dias_sem_chuva": "",
    "precipitacao": "",
    "risco_fogo": "",
    "bioma": "Amazônia",
    "frp": "4.8"
  },
  {
    "id": "dcc4901f-902e-3cf9-ab53-9137d512b304",
    "lat": " -12.906170",
    "lon": " -52.533960",
    "data_hora_gmt": "2026-01-11 00:49:00",
    "satelite": "TERRA_M-M",
    "municipio": "CANARANA",
    "estado": "MATO GROSSO",
    "pais": "Brasil",
    "municipio_id": "5102702",
    "estado_id": "51",
    "pais_id": "33",
    "numero_dias_sem_chuva": "",
    "precipitacao": "",
    "risco_fogo": "",
    "bioma": "Amazônia",
    "frp": "27.1"
  },
  {
    "id": "2387a6f0-0f08-3390-b977-60140f0104a7",
    "lat": " -11.855490",
    "lon": " -57.371660",
    "data_hora_gmt": "2026-01-11 00:49:00",
    "satelite": "TERRA_M-M",
    "municipio": "NOVA MARINGÁ",
    "estado": "MATO GROSSO",
    "pais": "Brasil",
    "municipio_id": "5108907",
    "estado_id": "51",
    "pais_id": "33",
    "numero_dias_sem_chuva": "",
    "precipitacao": "",
    "risco_fogo": "",
    "bioma": "Amazônia",
    "frp": "129.4"
  },
  {
    "id": "89248d93-b709-30a9-a0f6-8cbd84fd03f4",
    "lat": " -12.898080",
    "lon": " -52.531100",
    "data_hora_gmt": "2026-01-11 00:49:00",
    "satelite": "TERRA_M-M",
    "municipio": "CANARANA",
    "estado": "MATO GROSSO",
    "pais": "Brasil",
    "municipio_id": "5102702",
    "estado_id": "51",
    "pais_id": "33",
    "numero_dias_sem_chuva": "",
    "precipitacao": "",
    "risco_fogo": "",
    "bioma": "Amazônia",
    "frp": "9.8"
  },
  {
    "id": "9303381f-4d25-358b-985d-a63ae617ea14",
    "lat": " -12.913910",
    "lon": " -52.522740",
    "data_hora_gmt": "2026-01-11 00:49:00",
    "satelite": "TERRA_M-M",
    "municipio": "CANARANA",
    "estado": "MATO GROSSO",
    "pais": "Brasil",
    "municipio_id": "5102702",
    "estado_id": "51",
    "pais_id": "33",
    "numero_dias_sem_chuva": "",
    "precipitacao": "",
    "risco_fogo": "",
    "bioma": "Amazônia",
    "frp": "9.9"
  },
  {
    "id": "7cee569f-4829-3348-bbfe-857658ca4105",
    "lat": " -12.915350",
    "lon": " -52.532520",
    "data_hora_gmt": "2026-01-11 00:49:00",
    "satelite": "TERRA_M-M",
    "municipio": "CANARANA",
    "estado": "MATO GROSSO",
    "pais": "Brasil",
    "municipio_id": "5102702",
    "estado_id": "51",
    "pais_id": "33",
    "numero_dias_sem_chuva": "",
    "precipitacao": "",
    "risco_fogo": "",
    "bioma": "Amazônia",
    "frp": "12.7"
  },
  {
    "id": "a4155fb4-a35e-32a8-aad1-d2142578396f",
    "lat": " -16.589630",
    "lon": " -58.220740",
    "data_hora_gmt": "2026-01-11 00:49:00",
    "satelite": "TERRA_M-M",
    "municipio": "CÁCERES",
    "estado": "MATO GROSSO",
    "pais": "Brasil",
    "municipio_id": "5102504",
    "estado_id": "51",
    "pais_id": "33",
    "numero_dias_sem_chuva": "",
    "precipitacao": "",
    "risco_fogo": "",
    "bioma": "Pantanal",
    "frp": "14.6"
  },
  {
    "id": "134a2b79-a08a-3165-b576-ad73a0f310a5",
    "lat": " -12.904720",
    "lon": " -52.524170",
    "data_hora_gmt": "2026-01-11 00:49:00",
    "satelite": "TERRA_M-M",
    "municipio": "CANARANA",
    "estado": "MATO GROSSO",
    "pais": "Brasil",
    "municipio_id": "5102702",
    "estado_id": "51",
    "pais_id": "33",
    "numero_dias_sem_chuva": "",
    "precipitacao": "",
    "risco_fogo": "",
    "bioma": "Amazônia",
    "frp": "41.3"
  },
  {
    "id": "aaa414d4-1a8f-391d-865b-5bbe391642a7",
    "lat": " -15.618440",
    "lon": " -58.215640",
    "data_hora_gmt": "2026-01-11 00:49:00",
    "satelite": "TERRA_M-M",
    "municipio": "SÃO JOSÉ DOS QUATRO MARCOS",
    "estado": "MATO GROSSO",
    "pais": "Brasil",
    "municipio_id": "5107107",
    "estado_id": "51",
    "pais_id": "33",
    "numero_dias_sem_chuva": "",
    "precipitacao": "",
    "risco_fogo": "",
    "bioma": "Amazônia",
    "frp": "10.1"
  },
  {
    "id": "d7f0a631-18ad-3510-8e6d-34bc3c92c7c0",
    "lat": " -16.102770",
    "lon": " -56.751490",
    "data_hora_gmt": "2026-01-11 00:49:00",
    "satelite": "TERRA_M-M",
    "municipio": "POCONÉ",
    "estado": "MATO GROSSO",
    "pais": "Brasil",
    "municipio_id": "5106505",
    "estado_id": "51",
    "pais_id": "33",
    "numero_dias_sem_chuva": "",
    "precipitacao": "",
    "risco_fogo": "",
    "bioma": "Cerrado",
    "frp": "6.0"
  },
  {
    "id": "436f3bd5-4f5a-3637-ac80-2f4130e6a844",
    "lat": " -12.896670",
    "lon": " -52.521290",
    "data_hora_gmt": "2026-01-11 00:49:00",
    "satelite": "TERRA_M-M",
    "municipio": "CANARANA",
    "estado": "MATO GROSSO",
    "pais": "Brasil",
    "municipio_id": "5102702",
    "estado_id": "51",
    "pais_id": "33",
    "numero_dias_sem_chuva": "",
    "precipitacao": "",
    "risco_fogo": "",
    "bioma": "Amazônia",
    "frp": "6.3"
  },
  {
    "id": "0ef91901-ff94-388d-bb66-ea32b9c3cf91",
    "lat": " -16.591150",
    "lon": " -58.214800",
    "data_hora_gmt": "2026-01-11 00:49:00",
    "satelite": "TERRA_M-M",
    "municipio": "CÁCERES",
    "estado": "MATO GROSSO",
    "pais": "Brasil",
    "municipio_id": "5102504",
    "estado_id": "51",
    "pais_id": "33",
    "numero_dias_sem_chuva": "",
    "precipitacao": "",
    "risco_fogo": "",
    "bioma": "Pantanal",
    "frp": "22.6"
  },
  {
    "id": "0439f209-1d7e-3b35-8ab8-09f7adf32303",
    "lat": " -15.536310",
    "lon": " -55.762340",
    "data_hora_gmt": "2026-01-11 00:49:00",
    "satelite": "TERRA_M-M",
    "municipio": "CUIABÁ",
    "estado": "MATO GROSSO",
    "pais": "Brasil",
    "municipio_id": "5103403",
    "estado_id": "51",
    "pais_id": "33",
    "numero_dias_sem_chuva": "",
    "precipitacao": "",
    "risco_fogo": "",
    "bioma": "Cerrado",
    "frp": "5.3"
  },
  {
    "id": "1324381f-7f0b-3962-9473-cbde1bc93333",
    "lat": " -11.854090",
    "lon": " -57.360820",
    "data_hora_gmt": "2026-01-11 00:49:00",
    "satelite": "TERRA_M-M",
    "municipio": "NOVA MARINGÁ",
    "estado": "MATO GROSSO",
    "pais": "Brasil",
    "municipio_id": "5108907",
    "estado_id": "51",
    "pais_id": "33",
    "numero_dias_sem_chuva": "",
    "precipitacao": "",
    "risco_fogo": "",
    "bioma": "Amazônia",
    "frp": "32.9"
  },
  {
    "id": "30224927-f626-363e-8bd1-f8fb1e6d4d5a",
    "lat": " -15.620090",
    "lon": " -58.229660",
    "data_hora_gmt": "2026-01-11 00:49:00",
    "satelite": "TERRA_M-M",
    "municipio": "SÃO JOSÉ DOS QUATRO MARCOS",
    "estado": "MATO GROSSO",
    "pais": "Brasil",
    "municipio_id": "5107107",
    "estado_id": "51",
    "pais_id": "33",
    "numero_dias_sem_chuva": "",
    "precipitacao": "",
    "risco_fogo": "",
    "bioma": "Amazônia",
    "frp": "12.8"
  },
  {
    "id": "4db7724f-b3e8-3cc8-89e9-03324f69d3eb",
    "lat": " -15.527070",
    "lon": " -55.763650",
    "data_hora_gmt": "2026-01-11 00:49:00",
    "satelite": "TERRA_M-M",
    "municipio": "CUIABÁ",
    "estado": "MATO GROSSO",
    "pais": "Brasil",
    "municipio_id": "5103403",
    "estado_id": "51",
    "pais_id": "33",
    "numero_dias_sem_chuva": "",
    "precipitacao": "",
    "risco_fogo": "",
    "bioma": "Cerrado",
    "frp": "6.6"
  },
  {
    "id": "047c5306-c806-3711-9069-d7cf6b79dae1",
    "lat": " -11.853200",
    "lon": " -57.378100",
    "data_hora_gmt": "2026-01-11 01:00:00",
    "satelite": "GOES-19",
    "municipio": "NOVA MARINGÁ",
    "estado": "MATO GROSSO",
    "pais": "Brasil",
    "municipio_id": "5108907",
    "estado_id": "51",
    "pais_id": "33",
    "numero_dias_sem_chuva": "",
    "precipitacao": "",
    "risco_fogo": "",
    "bioma": "Amazônia",
    "frp": "62.3"
  },
  {
    "id": "b3c47924-f2d3-36a6-ad49-927a729bc9ae",
    "lat": "  -6.563100",
    "lon": " -51.112600",
    "data_hora_gmt": "2026-01-11 01:20:00",
    "satelite": "GOES-19",
    "municipio": "OURILÂNDIA DO NORTE",
    "estado": "PARÁ",
    "pais": "Brasil",
    "municipio_id": "1505437",
    "estado_id": "15",
    "pais_id": "33",
    "numero_dias_sem_chuva": "",
    "precipitacao": "",
    "risco_fogo": "",
    "bioma": "Amazônia",
    "frp": "67.9"
  },
  {
    "id": "e9f843fd-42b3-3c7a-baf3-6d607808475d",
    "lat": " -11.853200",
    "lon": " -57.378100",
    "data_hora_gmt": "2026-01-11 01:20:00",
    "satelite": "GOES-19",
    "municipio": "NOVA MARINGÁ",
    "estado": "MATO GROSSO",
    "pais": "Brasil",
    "municipio_id": "5108907",
    "estado_id": "51",
    "pais_id": "33",
    "numero_dias_sem_chuva": "",
    "precipitacao": "",
    "risco_fogo": "",
    "bioma": "Amazônia",
    "frp": "59.3"
  },
  {
    "id": "4a17948a-0f93-323a-b9ec-536589cdaf39",
    "lat": " -12.904100",
    "lon": " -52.515000",
    "data_hora_gmt": "2026-01-11 01:30:00",
    "satelite": "GOES-19",
    "municipio": "CANARANA",
    "estado": "MATO GROSSO",
    "pais": "Brasil",
    "municipio_id": "5102702",
    "estado_id": "51",
    "pais_id": "33",
    "numero_dias_sem_chuva": "",
    "precipitacao": "",
    "risco_fogo": "",
    "bioma": "Amazônia",
    "frp": "65.3"
  },
  {
    "id": "6796e8b5-d8b8-3eda-9bc2-5c525c8e2dd2",
    "lat": " -12.903800",
    "lon": " -52.536000",
    "data_hora_gmt": "2026-01-11 01:30:00",
    "satelite": "GOES-19",
    "municipio": "CANARANA",
    "estado": "MATO GROSSO",
    "pais": "Brasil",
    "municipio_id": "5102702",
    "estado_id": "51",
    "pais_id": "33",
    "numero_dias_sem_chuva": "",
    "precipitacao": "",
    "risco_fogo": "",
    "bioma": "Amazônia",
    "frp": "64.2"
  },
  {
    "id": "6540f742-b453-3f6b-b760-ec20160521a4",
    "lat": " -12.904100",
    "lon": " -52.515000",
    "data_hora_gmt": "2026-01-11 01:40:00",
    "satelite": "GOES-19",
    "municipio": "CANARANA",
    "estado": "MATO GROSSO",
    "pais": "Brasil",
    "municipio_id": "5102702",
    "estado_id": "51",
    "pais_id": "33",
    "numero_dias_sem_chuva": "",
    "precipitacao": "",
    "risco_fogo": "",
    "bioma": "Amazônia",
    "frp": "55.6"
  },
  {
    "id": "cca3673f-63fa-3968-b68d-4aec4b548c92",
    "lat": " -12.903800",
    "lon": " -52.536000",
    "data_hora_gmt": "2026-01-11 01:40:00",
    "satelite": "GOES-19",
    "municipio": "CANARANA",
    "estado": "MATO GROSSO",
    "pais": "Brasil",
    "municipio_id": "5102702",
    "estado_id": "51",
    "pais_id": "33",
    "numero_dias_sem_chuva": "",
    "precipitacao": "",
    "risco_fogo": "",
    "bioma": "Amazônia",
    "frp": "60.7"
  },
  {
    "id": "74a44691-fbc2-34db-a1d5-c48fda74ace8",
    "lat": " -11.853400",
    "lon": " -57.358200",
    "data_hora_gmt": "2026-01-11 01:50:00",
    "satelite": "GOES-19",
    "municipio": "NOVA MARINGÁ",
    "estado": "MATO GROSSO",
    "pais": "Brasil",
    "municipio_id": "5108907",
    "estado_id": "51",
    "pais_id": "33",
    "numero_dias_sem_chuva": "",
    "precipitacao": "",
    "risco_fogo": "",
    "bioma": "Amazônia",
    "frp": "55.2"
  },
  {
    "id": "edfa93cc-481b-3d30-adc4-be2d128ddbeb",
    "lat": " -11.853400",
    "lon": " -57.358200",
    "data_hora_gmt": "2026-01-11 02:00:00",
    "satelite": "GOES-19",
    "municipio": "NOVA MARINGÁ",
    "estado": "MATO GROSSO",
    "pais": "Brasil",
    "municipio_id": "5108907",
    "estado_id": "51",
    "pais_id": "33",
    "numero_dias_sem_chuva": "",
    "precipitacao": "",
    "risco_fogo": "",
    "bioma": "Amazônia",
    "frp": "68.3"
  },
  {
    "id": "e07b33ea-5e83-3fe1-84fb-cfd26086efdd",
    "lat": " -11.853200",
    "lon": " -57.378100",
    "data_hora_gmt": "2026-01-11 02:00:00",
    "satelite": "GOES-19",
    "municipio": "NOVA MARINGÁ",
    "estado": "MATO GROSSO",
    "pais": "Brasil",
    "municipio_id": "5108907",
    "estado_id": "51",
    "pais_id": "33",
    "numero_dias_sem_chuva": "",
    "precipitacao": "",
    "risco_fogo": "",
    "bioma": "Amazônia",
    "frp": "76.8"
  },
  {
    "id": "26da9416-9e88-3fcc-a94a-1d0113ed5c5e",
    "lat": " -11.872100",
    "lon": " -57.376600",
    "data_hora_gmt": "2026-01-11 02:00:00",
    "satelite": "GOES-19",
    "municipio": "NOVA MARINGÁ",
    "estado": "MATO GROSSO",
    "pais": "Brasil",
    "municipio_id": "5108907",
    "estado_id": "51",
    "pais_id": "33",
    "numero_dias_sem_chuva": "",
    "precipitacao": "",
    "risco_fogo": "",
    "bioma": "Amazônia",
    "frp": "60.6"
  },
  {
    "id": "44a1d538-ec29-34ab-beb9-af382011e1b7",
    "lat": " -11.853200",
    "lon": " -57.378100",
    "data_hora_gmt": "2026-01-11 02:10:00",
    "satelite": "GOES-19",
    "municipio": "NOVA MARINGÁ",
    "estado": "MATO GROSSO",
    "pais": "Brasil",
    "municipio_id": "5108907",
    "estado_id": "51",
    "pais_id": "33",
    "numero_dias_sem_chuva": "",
    "precipitacao": "",
    "risco_fogo": "",
    "bioma": "Amazônia",
    "frp": "70.8"
  },
  {
    "id": "07912c13-dc7e-3713-b70f-62d86f9ec2a0",
    "lat": " -12.903800",
    "lon": " -52.536000",
    "data_hora_gmt": "2026-01-11 02:10:00",
    "satelite": "GOES-19",
    "municipio": "CANARANA",
    "estado": "MATO GROSSO",
    "pais": "Brasil",
    "municipio_id": "5102702",
    "estado_id": "51",
    "pais_id": "33",
    "numero_dias_sem_chuva": "",
    "precipitacao": "",
    "risco_fogo": "",
    "bioma": "Amazônia",
    "frp": "55.0"
  },
  {
    "id": "57e89434-9e64-331e-821b-f47953c14b8f",
    "lat": " -11.853400",
    "lon": " -57.358200",
    "data_hora_gmt": "2026-01-11 02:10:00",
    "satelite": "GOES-19",
    "municipio": "NOVA MARINGÁ",
    "estado": "MATO GROSSO",
    "pais": "Brasil",
    "municipio_id": "5108907",
    "estado_id": "51",
    "pais_id": "33",
    "numero_dias_sem_chuva": "",
    "precipitacao": "",
    "risco_fogo": "",
    "bioma": "Amazônia",
    "frp": "72.3"
  },
  {
    "id": "7c8d993a-70be-347f-8498-fa119c6deb96",
    "lat": " -12.394300",
    "lon": " -58.050600",
    "data_hora_gmt": "2026-01-11 02:20:00",
    "satelite": "GOES-19",
    "municipio": "BRASNORTE",
    "estado": "MATO GROSSO",
    "pais": "Brasil",
    "municipio_id": "5101902",
    "estado_id": "51",
    "pais_id": "33",
    "numero_dias_sem_chuva": "",
    "precipitacao": "",
    "risco_fogo": "",
    "bioma": "Cerrado",
    "frp": "68.8"
  },
  {
    "id": "4594f2cc-6b62-3e94-aa57-6d7ad1b83d0c",
    "lat": " -12.413300",
    "lon": " -58.049000",
    "data_hora_gmt": "2026-01-11 02:20:00",
    "satelite": "GOES-19",
    "municipio": "BRASNORTE",
    "estado": "MATO GROSSO",
    "pais": "Brasil",
    "municipio_id": "5101902",
    "estado_id": "51",
    "pais_id": "33",
    "numero_dias_sem_chuva": "",
    "precipitacao": "",
    "risco_fogo": "",
    "bioma": "Cerrado",
    "frp": "63.2"
  },
  {
    "id": "ea29c6bc-927f-3149-98bc-553cf8db759f",
    "lat": " -12.903800",
    "lon": " -52.536000",
    "data_hora_gmt": "2026-01-11 02:30:00",
    "satelite": "GOES-19",
    "municipio": "CANARANA",
    "estado": "MATO GROSSO",
    "pais": "Brasil",
    "municipio_id": "5102702",
    "estado_id": "51",
    "pais_id": "33",
    "numero_dias_sem_chuva": "",
    "precipitacao": "",
    "risco_fogo": "",
    "bioma": "Amazônia",
    "frp": "53.6"
  },
  {
    "id": "bf232aa2-2353-3074-a3b6-e947421de04e",
    "lat": " -11.853400",
    "lon": " -57.358200",
    "data_hora_gmt": "2026-01-11 02:40:00",
    "satelite": "GOES-19",
    "municipio": "NOVA MARINGÁ",
    "estado": "MATO GROSSO",
    "pais": "Brasil",
    "municipio_id": "5108907",
    "estado_id": "51",
    "pais_id": "33",
    "numero_dias_sem_chuva": "",
    "precipitacao": "",
    "risco_fogo": "",
    "bioma": "Amazônia",
    "frp": "63.0"
  },
  {
    "id": "0395b927-d5ea-3335-b498-0573032b0fae",
    "lat": " -11.853200",
    "lon": " -57.378100",
    "data_hora_gmt": "2026-01-11 02:40:00",
    "satelite": "GOES-19",
    "municipio": "NOVA MARINGÁ",
    "estado": "MATO GROSSO",
    "pais": "Brasil",
    "municipio_id": "5108907",
    "estado_id": "51",
    "pais_id": "33",
    "numero_dias_sem_chuva": "",
    "precipitacao": "",
    "risco_fogo": "",
    "bioma": "Amazônia",
    "frp": "65.0"
  },
  {
    "id": "1f2523f2-115f-39bc-a76e-7c3816ce8ec4",
    "lat": " -11.853200",
    "lon": " -57.378100",
    "data_hora_gmt": "2026-01-11 03:00:00",
    "satelite": "GOES-19",
    "municipio": "NOVA MARINGÁ",
    "estado": "MATO GROSSO",
    "pais": "Brasil",
    "municipio_id": "5108907",
    "estado_id": "51",
    "pais_id": "33",
    "numero_dias_sem_chuva": "",
    "precipitacao": "",
    "risco_fogo": "",
    "bioma": "Amazônia",
    "frp": "66.3"
  },
  {
    "id": "39ddd84a-22e8-3b20-9d20-2f9b440e9074",
    "lat": " -11.853400",
    "lon": " -57.358200",
    "data_hora_gmt": "2026-01-11 03:00:00",
    "satelite": "GOES-19",
    "municipio": "NOVA MARINGÁ",
    "estado": "MATO GROSSO",
    "pais": "Brasil",
    "municipio_id": "5108907",
    "estado_id": "51",
    "pais_id": "33",
    "numero_dias_sem_chuva": "",
    "precipitacao": "",
    "risco_fogo": "",
    "bioma": "Amazônia",
    "frp": "56.0"
  }
]